serplint.py
serplint-1.4.0.dist-info/DESCRIPTION.rst
serplint-1.4.0.dist-info/METADATA
serplint-1.4.0.dist-info/RECORD
serplint-1.4.0.dist-info/WHEEL
serplint-1.4.0.dist-info/entry_points.txt
serplint-1.4.0.dist-info/metadata.json
serplint-1.4.0.dist-info/top_level.txt
